elabjournal/__init__.py
elabjournal/_version.py
elabjournal/elabjournal/Experiment.py
elabjournal/elabjournal/ExperimentFile.py
elabjournal/elabjournal/ExperimentFiles.py
elabjournal/elabjournal/ExperimentImages.py
elabjournal/elabjournal/Experiments.py
elabjournal/elabjournal/Group.py
elabjournal/elabjournal/Groups.py
elabjournal/elabjournal/Project.py
elabjournal/elabjournal/Projects.py
elabjournal/elabjournal/Sample.py
elabjournal/elabjournal/SampleMeta.py
elabjournal/elabjournal/SampleMetas.py
elabjournal/elabjournal/SampleSerie.py
elabjournal/elabjournal/SampleSeries.py
elabjournal/elabjournal/SampleType.py
elabjournal/elabjournal/SampleTypeMeta.py
elabjournal/elabjournal/SampleTypeMetas.py
elabjournal/elabjournal/SampleTypes.py
elabjournal/elabjournal/Samples.py
elabjournal/elabjournal/SamplesAndSeries.py
elabjournal/elabjournal/Section.py
elabjournal/elabjournal/SectionCanvas.py
elabjournal/elabjournal/SectionComment.py
elabjournal/elabjournal/SectionDatatable.py
elabjournal/elabjournal/SectionExcel.py
elabjournal/elabjournal/SectionFile.py
elabjournal/elabjournal/SectionImage.py
elabjournal/elabjournal/SectionMetas.py
elabjournal/elabjournal/SectionParagraph.py
elabjournal/elabjournal/SectionProcedure.py
elabjournal/elabjournal/SectionSample.py
elabjournal/elabjournal/Sections.py
elabjournal/elabjournal/Storage.py
elabjournal/elabjournal/StorageLayer.py
elabjournal/elabjournal/StorageLayers.py
elabjournal/elabjournal/StorageType.py
elabjournal/elabjournal/StorageTypes.py
elabjournal/elabjournal/Storages.py
elabjournal/elabjournal/Studies.py
elabjournal/elabjournal/Study.py
elabjournal/elabjournal/User.py
elabjournal/elabjournal/__init__.py
elabjournal/elabjournal/api.py
elabjournal/elabjournal/eLABJournalObject.py
elabjournal/elabjournal/eLABJournalPager.py
elabjournal-0.0.19.dist-info/LICENSE.txt
elabjournal-0.0.19.dist-info/METADATA
elabjournal-0.0.19.dist-info/WHEEL
elabjournal-0.0.19.dist-info/top_level.txt
elabjournal-0.0.19.dist-info/RECORD
