Metadata-Version: 2.1
Name: elabjournal
Version: 0.0.19
Summary: UNKNOWN
Home-page: https://github.com/matthijsbrouwer/elabjournal-python
Author: Matthijs Brouwer
Author-email: UNKNOWN
License: Apache License 2.0
Platform: UNKNOWN
Classifier: Framework :: Jupyter
Classifier: Intended Audience :: Science/Research
Requires-Dist: requests (>=2.18.4)
Requires-Dist: pandas
Requires-Dist: keyring
Requires-Dist: IPython
Requires-Dist: rjson
Requires-Dist: xlrd
Requires-Dist: matplotlib
Requires-Dist: Pillow
Requires-Dist: ipywidgets
Requires-Dist: graphviz
Requires-Dist: openpyxl
